portier/__init__.py
portier/cli.py
portier/config.py
portier/registry.py
portier/scanner.py
portier/utils.py
tests/__init__.py
portier_cli-0.1.4.dist-info/METADATA
portier_cli-0.1.4.dist-info/WHEEL
portier_cli-0.1.4.dist-info/entry_points.txt
portier_cli-0.1.4.dist-info/top_level.txt
portier_cli-0.1.4.dist-info/RECORD
