Metadata-Version: 2.4
Name: portier-cli
Version: 0.1.4
Summary: Gestionnaire de ports pour vos applications Docker
Home-page: https://github.com/Landers9/portier
Author: Franck AÏGBA
Author-email: franckaigba4@gmail.com
Project-URL: Bug Tracker, https://github.com/Landers9/portier/issues
Project-URL: Documentation, https://github.com/Landers9/portier#readme
Project-URL: Source, https://github.com/Landers9/portier
Keywords: docker,ports,cli,devops,containers
Classifier: Development Status :: 4 - Beta
Classifier: Environment :: Console
Classifier: Intended Audience :: Developers
Classifier: Intended Audience :: System Administrators
Classifier: License :: OSI Approved :: MIT License
Classifier: Operating System :: OS Independent
Classifier: Programming Language :: Python :: 3
Classifier: Programming Language :: Python :: 3.8
Classifier: Programming Language :: Python :: 3.9
Classifier: Programming Language :: Python :: 3.10
Classifier: Programming Language :: Python :: 3.11
Classifier: Topic :: System :: Systems Administration
Classifier: Topic :: Utilities
Requires-Python: >=3.8
Requires-Dist: click>=8.0.0
Requires-Dist: pyyaml>=6.0
Requires-Dist: docker>=6.0.0
Requires-Dist: rich>=13.0.0
Dynamic: author
Dynamic: author-email
Dynamic: classifier
Dynamic: description
Dynamic: description-content-type
Dynamic: home-page
Dynamic: keywords
Dynamic: project-url
Dynamic: requires-dist
Dynamic: requires-python
Dynamic: summary
